setup.py
msg_server.egg-info/PKG-INFO
msg_server.egg-info/SOURCES.txt
msg_server.egg-info/dependency_links.txt
msg_server.egg-info/requires.txt
msg_server.egg-info/top_level.txt
server/__init__.py
server/server.py
server/common/__init__.py
server/common/decos.py
server/common/descriptors.py
server/common/errors.py
server/common/metaclasses.py
server/common/settings.py
server/common/utils.py
server/log/__init__.py
server/log/client_log_config.py
server/log/server_log_config.py
server/server/__init__.py
server/server/add_user.py
server/server/config_window.py
server/server/main_window.py
server/server/remove_user.py
server/server/server_core.py
server/server/server_database.py
server/server/stat_window.py
server/unit_tests/__init__.py
server/unit_tests/test_client.py
server/unit_tests/test_server.py
server/unit_tests/test_utils.py