Metadata-Version: 1.0
Name: msg-server
Version: 0.0.2
Summary: messenger_server
Home-page: UNKNOWN
Author: Yanis Kachinskis
Author-email: yanis-k2000@yandex.ru
License: UNKNOWN
Platform: UNKNOWN
